README.md
setup.py
PhilippeCantrelle2ADatavizAutreAvecCarteTest4.egg-info/PKG-INFO
PhilippeCantrelle2ADatavizAutreAvecCarteTest4.egg-info/SOURCES.txt
PhilippeCantrelle2ADatavizAutreAvecCarteTest4.egg-info/dependency_links.txt
PhilippeCantrelle2ADatavizAutreAvecCarteTest4.egg-info/top_level.txt
philcantrel/Data_viz_a_packager_propre.py
philcantrel/__init__.py
philcantrel/module_carte.py